DESCRIPTION.rst
MANIFEST.in
README.md
RELEASE-VERSION
setup.cfg
setup.py
version.py
arduino_device/__init__.py
arduino_device/arduino_device.py
arduino_device.egg-info/PKG-INFO
arduino_device.egg-info/SOURCES.txt
arduino_device.egg-info/dependency_links.txt
arduino_device.egg-info/requires.txt
arduino_device.egg-info/top_level.txt