Metadata-Version: 1.1
Name: arduino-device
Version: 1.0
Summary: Interface to arduino devices with auto creation of class methods with arduino commands and auto discovery of available Arduinos in Linux, Windows, and Mac OS X
Home-page: https://github.com/JaneliaSciComp/python_arduino_device
Author: Peter Polidoro
Author-email: polidorop@janelia.hhmi.org
License: BSD
Keywords: arduino serial
Platform: UNKNOWN
Classifier: Development Status :: 3 - Alpha
Classifier: Intended Audience :: Developers
Classifier: Topic :: Software Development :: Build Tools
Classifier: License :: OSI Approved :: BSD License
Classifier: Programming Language :: Python :: 2.7
